amarillo_gtfs_generator/__init__.py
amarillo_gtfs_generator/gtfs.py
amarillo_gtfs_generator/gtfs_constants.py
amarillo_gtfs_generator/gtfs_export.py
amarillo_gtfs_generator/gtfs_generator.py
amarillo_gtfs_generator/utils.py
amarillo_gtfs_generator/gtfsrt/__init__.py
amarillo_gtfs_generator/gtfsrt/gtfs_realtime_pb2.py
amarillo_gtfs_generator/gtfsrt/realtime_extension_pb2.py
amarillo_gtfs_generator/models/Carpool.py
amarillo_gtfs_generator/models/__init__.py
amarillo_gtfs_generator/models/gtfs.py
amarillo_gtfs_generator/services/__init__.py
amarillo_gtfs_generator/services/agencies.py
amarillo_gtfs_generator/services/carpools.py
amarillo_gtfs_generator/services/regions.py
amarillo_gtfs_generator/services/trips.py
amarillo_gtfs_generator/tests/__init__.py
amarillo_gtfs_generator/tests/test_gtfs.py
amarillo_grfs_generator-2.0.1.dist-info/LICENSE
amarillo_grfs_generator-2.0.1.dist-info/METADATA
amarillo_grfs_generator-2.0.1.dist-info/WHEEL
amarillo_grfs_generator-2.0.1.dist-info/top_level.txt
amarillo_grfs_generator-2.0.1.dist-info/RECORD
