Metadata-Version: 2.1
Name: amarillo-grfs-generator
Version: 2.0.1
Summary: FastAPI app providing GRFS generation for Amarillo carpools
License: GNU AFFERO GENERAL PUBLIC LICENSE
License-File: LICENSE
Requires-Dist: amarillo
Requires-Dist: amarillo-stops
Requires-Dist: schedule
Requires-Dist: watchdog
